greb/__init__.py
greb/client.py
greb/mcp_server.py
greb/binaries/rg-darwin-amd64
greb/binaries/rg-darwin-arm64
greb/binaries/rg-linux-amd64
greb/binaries/rg.exe
greb/cli/__init__.py
greb/cli/__main__.py
greb/cli/main.py
greb/pipeline/__init__.py
greb/pipeline/base.py
greb/pipeline/code_analyzer.py
greb/pipeline/grep.py
greb/pipeline/read.py
greb/pipeline/search_context.py
cheetah_greb-2.1.2.dist-info/METADATA
cheetah_greb-2.1.2.dist-info/WHEEL
cheetah_greb-2.1.2.dist-info/entry_points.txt
cheetah_greb-2.1.2.dist-info/licenses/LICENSE
cheetah_greb-2.1.2.dist-info/RECORD
