Metadata-Version: 2.4
Name: cheetah-greb
Version: 2.1.2
Summary: AI-powered intelligent code search - client package with grep, read, and AST analysis (GPU reranking via cloud API)
Author-email: Greb Team <cheetahai69@gmail.com>
License-Expression: MIT
License-File: LICENSE
Keywords: ai,code-analysis,code-search,developer-tools,llm,mcp-server
Classifier: Development Status :: 4 - Beta
Classifier: Framework :: FastAPI
Classifier: Intended Audience :: Developers
Classifier: License :: OSI Approved :: MIT License
Classifier: Programming Language :: Python :: 3
Classifier: Programming Language :: Python :: 3.10
Classifier: Programming Language :: Python :: 3.11
Classifier: Programming Language :: Python :: 3.12
Classifier: Programming Language :: Python :: 3.13
Classifier: Programming Language :: Python :: 3.14
Classifier: Programming Language :: Python :: 3.15
Classifier: Topic :: Software Development :: Code Generators
Classifier: Topic :: Text Processing :: Indexing
Requires-Python: >=3.10
Requires-Dist: fastapi>=0.104.0
Requires-Dist: httpx>=0.25.0
Requires-Dist: mcp>=1.2.1
Requires-Dist: openai>=1.0.0
Requires-Dist: pydantic>=2.0.2
Requires-Dist: python-dotenv>=1.0.0
Requires-Dist: requests>=2.32.4
Requires-Dist: sse-starlette>=1.6.0
Requires-Dist: starlette>=0.27.0
Requires-Dist: tiktoken>=0.5.0
Requires-Dist: tree-sitter-language-pack>=0.7.0
Requires-Dist: tree-sitter>=0.24.0
Requires-Dist: uvicorn[standard]>=0.24.0
Provides-Extra: all
Requires-Dist: fastapi>=0.104.0; extra == 'all'
Requires-Dist: sse-starlette>=1.6.0; extra == 'all'
Requires-Dist: starlette>=0.27.0; extra == 'all'
Requires-Dist: uvicorn[standard]>=0.24.0; extra == 'all'
Provides-Extra: dev
Requires-Dist: black>=23.10.0; extra == 'dev'
Requires-Dist: isort>=5.12.0; extra == 'dev'
Requires-Dist: mypy>=1.6.0; extra == 'dev'
Requires-Dist: pytest-asyncio>=0.21.0; extra == 'dev'
Requires-Dist: pytest>=7.4.0; extra == 'dev'
Requires-Dist: ruff>=0.1.0; extra == 'dev'
Provides-Extra: mcp
Requires-Dist: sse-starlette>=1.6.0; extra == 'mcp'
Requires-Dist: starlette>=0.27.0; extra == 'mcp'
Provides-Extra: server
Requires-Dist: fastapi>=0.104.0; extra == 'server'
Requires-Dist: uvicorn[standard]>=0.24.0; extra == 'server'
